<org.spantus.externals.recognition.bean.CorpusFileEntry>
  <featureFrameValuesMap>
    <entry>
      <string>smooth_ENERGY_EXTRACTOR</string>
      <org.spantus.core.beans.FrameValuesHolder>
        <values>
          <SeriesOfScalar totalNumOfSamples="94" sampleRate="296.2962962962963">
            <Raw>170131.87193102436 242252.5804062771 379526.1698479622 508147.3548761091 701630.2561119435 926930.8860640216 1141503.0534856312 1355130.9065001272 1567673.881658588 1748919.5117928989 1907833.6824127682 2038134.0202838378 2157377.4973642337 2238533.8297256604 2285907.951958954 2324243.9924921514 
2346305.12032756 2362086.890647835 2374568.4151811493 2385215.637027015 2499464.919556305 2599753.4430266465 2682972.8289269023 2745055.7999848574 2767656.374232268 2753991.063611981 2705215.9436675063 2623469.1540029254 2509670.3355965666 2382388.7532603485 2238657.1242180094 
2082244.4023390042 1917605.127505545 1761864.1641180362 1619672.3035434599 1478953.2286049412 1347670.1793971288 1218602.6524178411 1089934.2657280387 961398.7124971742 839253.4105875622 723800.3784267423 608489.8645691902 502357.0983435976 406579.10869262856 318093.1876175933 
245940.18158235282 185713.46081202815 136670.60531127045 95472.27142654709 64866.263226719784 48182.04134115855 33868.10077407146 25445.045787621508 20751.783459579165 17069.758399229268 13898.822899070092 11956.292473812935 11173.569633407731 10827.827200118138 10675.786454581794 
10540.64563474183 10398.538726361554 10272.892720763784 10190.796159768648 10225.409478522744 10284.278078893512 10382.948022442182 10568.943135695974 10842.075212119635 11139.688602339884 11360.23434715083 11471.662480262556 11499.9303113311 11439.462826141862 11401.303059575504 
11344.993896232454 11139.75330604485 10855.79520303523 10581.054766704206 10387.401749530973 10273.312178637805 10116.748056398124 9868.222090215515 9569.251467343516 9206.078173677452 8853.805213981977 8488.153779602628 8056.80252897575 7538.063753236691 6973.80354536756 
6523.603825880127 6215.919404616754 5934.811502096679 </Raw>
          </SeriesOfScalar>
        </values>
        <sampleRate>296.2962962962963</sampleRate>
      </org.spantus.core.beans.FrameValuesHolder>
    </entry>
  </featureFrameValuesMap>
  <featureFrameVectorValuesMap>
    <entry>
      <string>MFCC_EXTRACTOR</string>
      <org.spantus.core.beans.FrameVectorValuesHolder>
        <values>
          <SeriesOfVector totalNumOfSamples="94" sampleRate="296.2962962962963" vectorSize="12">
            <Raw>7920931.395275531 5915914.886155525 1985722.7085080626 423241.8208760551 1931329.0155577017 2172660.4120116374 1036888.9402372544 729518.9156772185 861465.9040118497 205900.35281895092 7544.470494972468 0.0 2767204.5371753625 7821605.215623295 2755007.5690211486 304611.5269775282 
1051813.2048967353 892135.6794004887 950932.7149313606 763531.4695780901 1406525.5512789737 1745359.8862751508 126291.25752657134 0.0 3453660.4188625086 1.801742764053484E7 9292396.532653106 1192985.374620514 2531247.5977607896 1845126.7438235201 2533725.0254626167 
2907386.203398982 1494355.9629267866 4279746.481114989 273900.8429275496 0.0 581463.7571126815 1.32560646675338E7 5529550.546964021 1758801.793381605 835650.3062916979 1255540.3236717766 5019874.772130921 1898527.1548861715 1773407.1300887612 1546289.74711211 
83302.64505514267 0.0 9815508.587549653 4.2933924158083744E7 1.6637001311407842E7 4290912.75152332 4069605.7401224575 7009305.001701549 4130394.984254094 4369523.46032927 1872184.9150763499 1371005.5122512442 72687.10069622769 0.0 1.3641303863749318E7 
4.7131477982794195E7 1.8366353937925003E7 3034172.395780404 4048390.528911133 3564388.8205635934 2940966.049515781 4201571.714324104 1915976.5207858428 2100956.523448644 136725.233613809 0.0 6011753.838687765 3.1184118984413944E7 1.5528206405061178E7 3272148.859927156 
782472.5471165178 1278109.885324608 1581209.6369353312 685524.5407174013 1526494.7149376418 2736634.297932421 206929.1896575751 0.0 1464060.4427156188 3.1227497342803404E7 1.2038830715726297E7 367567.86433284206 2041432.5765798234 2934906.958890665 2910704.8897031085 
1604299.0302312262 3818743.549846801 4034783.56626371 68220.57184499662 0.0 1863085.5651287136 3.138436955817481E7 1.245976610513902E7 710973.2818667545 1612324.4483297616 2257739.397377803 2219211.6891412362 1282181.7388593752 3487241.625183947 4907244.776363244 
40465.958477391476 0.0 2355804.2610079087 1.8232012500214834E7 3688364.4399306145 1983256.0138197183 5148102.939567239 2611813.441506625 2031229.5962635388 2027569.7644275362 2511733.3341274383 1498148.132310838 24658.726858356356 0.0 631624.044967775 
1.4374103006239278E7 6858182.858379969 746638.1117035946 1962984.017111606 1568017.11141475 2973349.246818662 2541365.6088151736 2825366.0553833726 1660649.0947759578 130778.3824640843 0.0 6311891.514766663 2.3858769769550454E7 5020970.557366142 1401244.2890644462 
1413230.5981725252 2173241.3490249845 1794839.55902969 1185964.9745191806 3044886.6042028777 2711599.511334725 64106.20024195644 0.0 4954662.762266126 1.8517408947406735E7 8223371.898253495 1823023.087561051 1567990.5364353077 3070074.4152280604 2567579.7203358384 
1982466.329313261 2804216.99722547 3135443.273073524 141071.10965235686 0.0 5242934.212791447 1.900683569778468E7 6724593.049978186 2168369.775750215 3315759.2074919855 2567946.663953922 2280892.828831085 1427726.7356000168 1513466.958008645 1867155.2007305862 
44149.34406114984 0.0 4930375.659993758 1.2825792786679944E7 4859115.364805821 1290065.1152064612 2361481.382902799 2622935.1949590445 1901551.1747003242 760237.1705313782 1532378.6110192935 687410.0541208355 47423.82550101779 0.0 5704506.925997849 
2.2171329315851312E7 1.0249193308046067E7 2434473.2075556736 1550647.6445562607 1682584.0769175412 4011738.9766683416 2080007.2487568925 2301026.9451167365 427978.9257270113 13787.995272921256 0.0 5050975.756817493 1.0266320588495309E7 3648991.860095684 1730172.3104218543 
1519127.3922554117 1173059.9291478505 2885160.3760897513 1741737.9733979462 2028837.0446608707 1178081.7915049712 47320.1082729231 0.0 4118783.6640343685 3.0480709502916977E7 1.1079465645624354E7 639283.8707842119 2098511.710556844 1382028.3065211128 3047374.019957568 
1305836.4834102758 2172680.0084677353 1108433.3779341842 9670.832490591181 0.0 3506261.262434881 2.2513150462444328E7 7548049.256906946 485991.00706417114 477505.2994145051 751138.2170617267 1792789.6208063625 1157084.337740552 2687621.8182523195 1208135.9586042555 
12967.047672164183 0.0 3241937.462362924 1.2983120601542613E7 3171437.721578711 2742942.420078279 2132338.9650818016 3199914.2239132985 2467153.018193894 1835082.3241447404 2720167.0936984257 1408342.4027446671 39657.43475012353 0.0 1771920.8745449276 
1.4151452582227264E7 4341025.260578556 2378067.0842672084 1223148.0560725816 704969.1095258755 1572207.0332104212 1565370.91814799 794711.833148266 824814.4948656131 38017.714586714865 0.0 8557648.116107088 1.4761742045909535E7 4414649.06782823 2111974.32307401 
704158.9103757374 1385044.3133300028 1045241.9840594447 1652744.6323391264 1293571.3087058063 630695.7681550888 24492.380394201817 0.0 1.3531228920260295E7 1.6485994951082844E7 4014653.545371068 892074.3384525013 513762.5493479712 2499786.0896830247 2288479.9993375908 
2630859.1170702586 1714365.9175507624 1113169.7885448965 63613.64254488569 0.0 953045.1179285948 2382253.0948081478 659907.078801565 135455.028057892 305674.3142638392 875923.5497616027 890746.0974819727 403133.1557395645 269000.72944993514 225612.8570645918 
2395.9633039152473 0.0 6917087.088877762 4313540.739165044 535731.2742633971 210009.39355675963 420392.68284256593 652961.855448056 1061834.220188859 482143.7668813456 320472.18467538484 391365.4785462584 22111.226737022036 0.0 5482774.849391723 
2280334.4881792422 570171.3933344218 133686.44499267137 271211.10264131764 613423.9469766122 409437.1164884513 323346.4672175414 476396.2429465512 213825.55844494095 6688.221305081524 0.0 1426715.1452282441 886112.2997375049 212509.93831648628 88113.60188104089 
140442.6261351154 204694.4290272149 133132.53319600897 92528.99628931098 189564.94872967462 118241.82142085204 2997.210837077543 0.0 381610.78718969383 274005.5864771527 140531.8188174416 199291.6857258941 164645.8967427095 62775.0888422228 108348.87729842191 
107154.15435950633 91860.60100446311 42888.26782302348 885.5355720402239 0.0 1457917.330138375 966102.3977981248 359063.0606015053 152316.34269231948 106628.75914460992 85389.0355185189 142607.1665839283 103268.91503186602 171494.822503183 129845.68185085917 
2373.173658778926 0.0 805435.3908282103 1475086.5409110873 478669.1651647689 256452.76017985327 245835.20324402433 120862.84080475924 150698.793763483 42407.50602698909 46318.23290421479 40602.0813960723 4194.361065135219 0.0 244308.09251563743 
691419.4270616468 159855.87441814734 121957.69808104768 82481.31974763834 82141.63065784544 84159.97267536128 16060.104723230555 31673.104835113838 34476.59841971304 3860.196646076901 0.0 106552.12421437995 226935.92845992759 63225.281159082595 20064.97616589376 
10752.339316827574 27491.26071567416 25102.00639229818 18479.03524464337 68458.49145146953 102984.26629776348 6613.076382999204 0.0 67339.65855813328 35700.36040079696 17136.599576276552 8536.821198170295 2149.402253731479 18229.308945137986 16722.33504458387 
19101.1387971691 25016.24750781356 42612.20162584246 1672.9767423456801 0.0 20252.250901089927 32988.40080970924 15778.845093630996 2250.256025681269 785.5318092764142 4590.904336424991 3967.909140366888 3618.514656239753 4973.129367824563 9466.822651652092 
458.02444375838564 0.0 9354.303712771663 25109.17718511357 13975.510124326709 2313.639275860369 1023.7652422611725 5669.56480259324 3963.9642698351768 4004.3686722010657 3451.0039813056364 6670.473179102071 384.6846150527477 0.0 25099.54293320845 
60014.47415071827 24661.924083599806 2184.474169432239 2975.0329765896636 7903.559667790586 10567.089588425319 12553.40422849032 6939.567262140705 6670.78500391451 750.888940132059 0.0 23356.582119377596 81973.15411294073 26132.323172573913 1356.4636879315171 
2580.8226572963194 2614.6330611435264 5308.512105897254 18292.369075345705 16860.43360581153 12323.533156031983 890.5861289304804 0.0 3936.663037229704 77765.14888795203 17560.118047229265 1147.248488176639 5169.028839826641 4441.751984132105 3060.6266154104915 
4584.797118591952 12593.869680292059 19140.27679257792 700.2394318792541 0.0 10111.746291660098 53412.80360540663 12640.948020674026 6082.126954067483 7724.485975291404 7890.7862435288735 4701.24470142867 5731.863020917925 8747.635534318844 18877.99341439153 
919.2490367348441 0.0 11846.45663851966 19905.823505236804 12357.222310631862 4098.805836653445 4875.69643920328 2768.0929880858876 1174.7133335524175 1397.7689840556816 1950.0263029297466 2899.7620032288514 238.8918687503159 0.0 15982.923040660362 
16827.8506147636 11418.313563975431 6179.169773146461 13433.299509116921 16652.719370256702 4828.96121775615 2692.0804812864826 2524.2466075741336 1226.970686812373 11.278943033950169 0.0 12536.376959797248 49048.441182547576 30611.786931795206 26097.918306813102 
17943.439360999648 12195.693504042594 5934.151769656958 2928.7229946367675 5893.272238296163 4427.837875697257 244.680466805288 0.0 35765.25071383521 69469.57727644475 35829.27372872535 15071.333617668737 6423.721306130276 3429.57211250313 4070.897611924181 
2517.4716852407287 4774.465198320244 4448.757760087883 185.67737632380855 0.0 26153.74930735921 79166.41872261961 30124.265579625942 5477.275617438616 5513.833056340068 8482.657665999595 6745.574922878511 7458.999306249277 11011.513685582515 9619.026371947846 
110.07173447644485 0.0 4462.526977120655 17259.07926531489 8140.250886314908 5774.336537456956 8791.217071111769 4112.755598139277 1363.5506718956458 2504.59510692054 4293.652866737922 3862.677538603336 51.26806551484998 0.0 6137.221660542607 
7968.9884308887995 5638.542462210914 2523.0023087737745 6017.984415489698 8188.888365512549 967.3435806634564 1835.097888220553 1928.7303892666448 1531.435899914922 114.83708404597448 0.0 13636.888100510896 11704.424332374005 14622.626155222291 7022.820618136238 
4409.151249395751 7576.054703563702 3160.811388188292 4171.482439333963 4770.022454713738 3163.1311345018744 97.50806403155396 0.0 12903.04913444983 36323.09526941873 9584.911248328932 7121.855067862954 5776.512432310999 6917.897760659951 12008.894782558937 
15048.51633885931 5402.40561933174 1640.7713440201405 99.87206115837897 0.0 6211.003696822847 27669.19318519663 11746.739828049167 2028.027520111316 1655.3921995446865 2375.764639782927 4312.843704653944 5495.293019730552 4615.839921936695 2645.771783037389 
166.40246376622895 0.0 16936.986950668204 14132.18712844776 14392.760766181325 9989.570144102849 2900.3646090620337 2073.365685693273 11927.636277734164 7580.880285096581 6307.228109987881 3701.7592088859633 148.17712807258548 0.0 60606.88259729631 
53475.71627818049 10957.72148797781 5776.698833519725 12528.564131846073 6255.469903124219 6662.181147840408 7353.085166002664 21169.754761068787 8680.753505286448 981.7555288770468 0.0 13602.256177549523 28177.952116026467 7633.416835353382 4340.06169506424 
7840.128180728471 3614.049532103148 5343.935666264456 4057.2223949184095 5171.354937284991 7224.576340028052 896.0317284447165 0.0 22312.733216139073 2247.9561251549103 2296.314107646814 3148.412303001813 7319.164354801573 6713.025031830719 8356.320762943953 
3219.553257989324 3522.5714029625915 11273.44856744172 157.52349159439356 0.0 50593.84907383695 36311.40471716702 17626.546477117674 9763.158137804248 5731.111256672694 4522.561684635943 4747.3634559718175 3068.395713840799 6217.614308513663 4834.387725651154 
198.0981498628756 0.0 63255.46622261105 53509.15384433673 13410.483815080599 4485.763636351485 4319.340939048971 2363.111412752404 5432.336325256297 4107.761754425107 11092.915856528589 4495.874100035789 24.694847578254972 0.0 957.8041098383742 
8567.34193535484 10938.063770126384 5269.994758161985 6589.761342287722 2526.1025742623924 4326.457471963514 3288.5449743357963 5951.272316418947 4632.210713851982 25.695173121383775 0.0 12014.118536572081 1707.9341397642231 3351.61766910788 4087.467118668361 
6533.200101137766 5210.737389281736 5010.719546690422 2496.5080553725493 5611.678914938612 5269.020729807504 23.3529979681496 0.0 15914.41651094843 19728.089287405095 14246.180928151207 5569.1580591388065 4059.771810931277 3146.472157804984 6743.352356599363 
4987.980857116131 4874.255390845702 4946.981599497293 152.1765310822879 0.0 5413.779989233036 10437.856566109967 10958.044626582941 2147.564365991981 1759.3104807630202 2121.044260464061 2881.6174218628107 3948.543676973683 6598.748551412444 5453.783286099354 
94.13267562702687 0.0 6079.350166640822 6109.198487964461 5364.462795574749 4626.043023985749 8477.97360482121 8358.872315230043 6042.402544747751 4243.78619008553 3064.4293738055417 3933.4371653227454 117.33319121885636 0.0 13665.463960438368 
7722.065789447489 1297.6545248294133 1418.1439675768524 3877.7638622806726 4870.392345879118 2676.5733568913174 1153.6509076418208 609.3766118708505 3422.1364561145792 474.1396425477345 0.0 4148.798349476153 5629.608666879551 4498.749763716571 1903.3153557710918 
1948.1591247952824 7952.859900086131 4235.849784886334 3886.7152901538007 2131.6821650062366 3424.8567624696993 228.95864626678832 0.0 12775.639001512247 28310.909687115713 24452.15923008111 9456.56779255916 12091.595395000033 45406.88345729976 15536.997052767134 
6875.273135756377 10259.797937808366 4504.109306580989 129.80400813215476 0.0 13437.925477638872 31250.92626225606 19703.945333798405 7581.7585545945085 3123.04407987061 13824.777785852653 8136.751297832834 4094.224156967002 10372.261070022085 17567.253643955144 
1296.3360716493455 0.0 10397.667521499221 4546.983549013177 5917.010947417465 9112.39079946011 6786.227461639335 8438.316233928976 6633.063147993898 3312.745900140135 5074.543279204938 5121.660680289929 164.9628478412717 0.0 24967.663905159923 
10711.520406623482 5043.824702726998 11426.34244211062 4723.202196688034 21295.565739485304 41491.26700014945 7895.055943007737 8602.04732628479 9296.090565686638 69.08926982054335 0.0 6786.607818393489 17268.087464926855 14918.660998916954 7031.549379097044 
13633.343229990218 14218.810208825418 23917.57523281138 5156.339260512655 12701.954252896712 6931.919105273065 91.29452431371718 0.0 14837.091527299457 27078.169567000514 16103.301929386484 6677.933119948346 5262.023480485192 4875.884967464793 7954.474179519744 
9921.983245852058 11401.231424970301 4055.1547245970314 234.3099419862474 0.0 19324.3214100345 40790.02408491268 25006.22422253954 13964.24454418657 11131.438131401457 16294.71847207711 21228.829440585483 8375.18875580928 9057.384037914046 9726.274826593566 
1076.8379456002876 0.0 23183.454325390623 19374.997894466418 15280.832804973928 4139.4978404338235 5965.616748234573 11533.41324708548 5513.143100801296 4250.705620897546 5289.883636471514 6182.307072570675 720.7728312971085 0.0 6633.170744324776 
31180.034406317238 8188.607682269456 982.7454896511476 2607.9140198225045 1726.732202081309 495.6143738089675 878.8778286772339 1183.7869367563153 3078.6234779353526 108.80515342519688 0.0 5030.953055147441 15534.184623467152 3949.5751380302936 3254.1450292732334 
2800.130952714846 1585.667590621472 421.631769182719 504.9932479468402 1073.454534257009 2197.189188221445 77.52033028480176 0.0 981.7429535282663 798.0023481262346 1443.979898175541 2345.5557158958964 3413.2083126004686 3589.500094301041 2131.4030856904888 
1258.7781926490882 2605.592596035154 1297.0121306194762 58.851591646694104 0.0 7661.652175910058 3450.458037443288 2138.0045580058186 2590.093208279131 651.8140129520534 1026.392920571893 1413.6894195641066 789.299126189178 1457.614612004904 2245.483227167281 
106.97490997804977 0.0 10654.626418884607 12029.935000162408 4155.457081546245 5168.619143898872 2139.049778107475 957.2575792744318 1206.6991332121404 1605.2022068963975 6366.39855446329 10505.519084136213 241.20894755614006 0.0 4074.331036073202 
3575.6862512877296 4906.6277722021105 2697.053690155537 5956.185035190487 6049.334387813439 7297.769097913342 5484.304578710493 8478.862336338654 15724.006462244944 578.7081507771751 0.0 7569.016211320015 11678.325751351305 2606.044399314018 835.6347624840066 
2191.3154806837615 4561.927696798419 3977.064806622287 3489.9529465919804 9286.618579392234 4213.099302297112 162.97429214609804 0.0 1668.1014101106211 2999.932068759106 906.9285684978328 404.4369599502102 1071.251904634922 885.6873266001488 486.6203142077304 
573.0774422937687 893.0702612925088 264.40469986096537 8.007859104898095 0.0 2360.5195092070658 1336.1275417374245 1428.8853879842766 1189.026368012385 868.2109285416477 624.7071570919138 390.6608126559426 138.35139499451185 121.36475856731977 206.22249253765779 
7.322875218635782 0.0 9259.25839523453 9154.993093613104 4293.988499350778 2813.848983907464 2558.3335966346267 2266.137302949803 1278.3080078403568 2594.287325088818 5115.984591779897 1422.7879561939978 10.598171549084437 0.0 7229.223320714402 
2333.3355015700745 734.864636236516 3617.6937210979186 2141.440463314134 1838.0883151352393 1346.9780076281236 5349.394990933571 17015.279670649128 6271.370452159175 30.448193057737548 0.0 9837.140212519413 2827.8684067443437 2021.874765112855 2113.492397368973 
3331.8391429893773 824.5126252384043 562.0810782325495 2478.8907919079065 14451.116783747528 7448.68253627593 103.16094209133988 0.0 11277.295973342552 7370.4141861587705 1285.4761554771724 1009.3124761170968 1101.490872279635 349.3151523005877 592.3513294689279 
1631.274925373261 6610.3594967375 5237.267952179271 197.07580528922097 0.0 2057.881816325341 1217.843848936132 675.3518042503548 273.74252918887373 87.07993719958785 45.18660719259891 86.99368844274593 101.88179761233866 702.0195341817334 854.8218068603564 
61.454499184045275 0.0 7212.89582605402 7477.129964454223 4337.308858801594 1439.843096296029 514.0319025809797 317.31230632284615 1353.9101681836912 1253.0018893730569 3487.7472936605986 2656.80352435149 141.16849291936228 0.0 4716.723599839892 
4521.459333959357 3349.359663215371 1460.6558824167903 1441.9419972899877 563.3197150478635 2036.2737483617382 3172.7545507252426 4622.731356251223 806.2496030537181 30.641188808720905 0.0 13265.08177854264 7779.568121123256 4851.153808521978 1602.1198435948756 
5011.579753059831 3893.0824582764767 4115.007849127396 10339.663399641178 18250.8904627771 1780.2699618326424 21.529782246781615 0.0 12766.559337076354 13812.610148045687 6730.241289885357 4686.926742647502 3573.0769714599583 3050.9927317561956 8952.324246773253 
11486.888480656191 14343.408462418043 1573.112691369735 2.457938203660075 0.0 4740.768799981919 6345.324393537833 5321.170916411031 3707.681567704579 1790.8648512856626 1084.502741103355 2116.302874224342 3340.215251161226 10722.678957389999 10104.992573801423 
37.35521156339004 0.0 2765.7378318906003 6057.133108554444 3130.3527142928738 3010.89992808935 742.2965078048396 1339.4609994514371 2887.7623990472393 3386.8451046870655 7335.270482774014 5223.783081092012 57.04862320526932 0.0 3065.8540284383635 
12970.14066391093 4741.112265475764 2135.7491749136116 843.5913783223938 2148.188674382882 2952.6527817217698 1441.1286007085362 1005.8704987576353 684.3385958967613 36.99210309234542 0.0 4120.794809081978 20906.522901830132 8032.271149373226 2521.427800713597 
3841.3750106378707 3545.1339298279245 1658.67533192312 4505.457878441169 4200.3796655786155 307.46152001400014 9.148513352655014 0.0 3720.440694379994 12680.761860824769 7438.015776069166 3639.5328339332086 3540.5657645442934 2901.1296219509304 2268.848276552586 
5453.68745629385 4587.289723729287 2414.753621936142 181.5238821315453 0.0 1930.0633958366625 2668.5125955641406 1509.434936075668 957.5844106638701 997.5510010664475 1426.5140463807436 1749.0166679305958 2120.053244748809 1884.556427117275 1609.3406274988026 
58.7087241059797 0.0 </Raw>
          </SeriesOfVector>
        </values>
        <sampleRate>296.2962962962963</sampleRate>
      </org.spantus.core.beans.FrameVectorValuesHolder>
    </entry>
  </featureFrameVectorValuesMap>
  <name>da</name>
  <id>1349722230065</id>
  <entryFile>/home/as/src/git.spnt/data/CORPUS/phone/da-1349722230065.cspnt.xml</entryFile>
  <wavFile>/home/as/src/git.spnt/data/CORPUS/phone/da-1349722230065.wav</wavFile>
</org.spantus.externals.recognition.bean.CorpusFileEntry>